dispbind/DISPbind.py
dispbind/__init__.py
dispbind/align.py
dispbind/bam2bw.py
dispbind/helper.py
dispbind/island.py
dispbind/main.py
dispbind/signal.py
dispbind/version.py
DISPbind-1.1.0.dist-info/LICENSE.txt
DISPbind-1.1.0.dist-info/METADATA
DISPbind-1.1.0.dist-info/WHEEL
DISPbind-1.1.0.dist-info/entry_points.txt
DISPbind-1.1.0.dist-info/top_level.txt
DISPbind-1.1.0.dist-info/RECORD
